rounder/__init__.py
rounder/rounder.py
rounder-0.7.1.dist-info/LICENSE
rounder-0.7.1.dist-info/METADATA
rounder-0.7.1.dist-info/WHEEL
rounder-0.7.1.dist-info/top_level.txt
rounder-0.7.1.dist-info/RECORD
